one_extract/__init__.py
one_extract/_version.py
one_extract/cli.py
one_extract/enc.py
one_extract/one.py
one_extract/py.typed
one_extract-0.1.3.dist-info/METADATA
one_extract-0.1.3.dist-info/WHEEL
one_extract-0.1.3.dist-info/entry_points.txt
one_extract-0.1.3.dist-info/licenses/LICENSE.md
one_extract-0.1.3.dist-info/RECORD
