Metadata-Version: 2.4
Name: one-extract
Version: 0.1.3
Summary: Simple extractor for OneNote files.
Project-URL: Documentation, https://github.com/volexity/one-extract/blob/main/README.md
Project-URL: Issues, https://github.com/volexity/one-extract/issues
Project-URL: Source, https://github.com/volexity/one-extract
Author-email: Threat Intel <threatintel@volexity.com>
License-File: LICENSE.md
Keywords: extractor,onenote
Classifier: Development Status :: 4 - Beta
Classifier: License :: OSI Approved :: BSD License
Classifier: Programming Language :: Python
Classifier: Programming Language :: Python :: 3.8
Classifier: Programming Language :: Python :: 3.9
Classifier: Programming Language :: Python :: 3.10
Classifier: Programming Language :: Python :: 3.11
Classifier: Programming Language :: Python :: 3.12
Classifier: Programming Language :: Python :: Implementation :: CPython
Classifier: Programming Language :: Python :: Implementation :: PyPy
Requires-Python: >=3.8
Requires-Dist: msoffcrypto-tool~=5.0
